[
  {
    "id": "orientation",
    "title": "ปฐมนิเทศ",
    "dateShort": "ก.ค.",
    "compareDate": "2026-07-04",
    "imageUrl": "https://images.unsplash.com/photo-1523580494863-6f3031224c94?q=80&w=600&auto=format&fit=crop",
    "type": "activity",
    "shortDesc": "กิจกรรมต้อนรับน้องใหม่และแนะนำการใช้ชีวิตในรั้วมหาวิทยาลัย",
    "details": {
      "info": "กิจกรรมแรกสุดที่น้องๆ จะได้เจอกับเพื่อนๆ ในรุ่นและรุ่นพี่ มีการแนะนำคณะ กฎระเบียบ การลงทะเบียนเรียน",
      "duration": "ครึ่งวัน (ประมาณ 08:00 - 12:00 น.)",
      "roles": "น้องปี 1 เข้าร่วมในฐานะผู้เข้าร่วมกิจกรรม จัดโดยคณาจารย์คณะวิศวกรรมศาสตร์"
    }
  },
  {
    "id": "first-date",
    "title": "กิจกรรม First Date",
    "dateShort": "ก.ค.",
    "compareDate": "2026-07-19",
    "imageUrl": "https://images.unsplash.com/photo-1526976663112-001524a6bc41?q=80&w=600&auto=format&fit=crop",
    "type": "activity",
    "shortDesc": "กิจกรรมพบปะกับเพื่อนๆที่จะเรียนไปด้วยกันตลอดปี 1 พร้อมการลงทะเบียนเรียน",
    "details": {
      "info": "กิจกรรมกลุ่มย่อย เน้นพบปะกับเพื่อนๆ คุยกับเพื่อนใหม่ครั้งแรก",
      "duration": "1 วัน",
      "roles": "ปี 1 เป็นผู้เข้าร่วม ผู้จัดหลักๆเป็นรุ่นพี่"
    }
  },
  {
    "id": "vishnu",
    "title": "ค่ายวิษณุกรรมบุตร",
    "dateShort": "ก.ค.",
    "compareDate": "2026-07-22",
    "imageUrl": "https://images.unsplash.com/photo-1526976663112-001524a6bc41?q=80&w=600&auto=format&fit=crop",
    "type": "activity",
    "shortDesc": "ค่ายละลายพฤติกรรมครั้งแรกของนิสิตน้องใหม่ของคณะวิศวกรรมศาสตร์",
    "details": {
      "info": "ค่ายที่ละลายพฤติกรรมน้องปี 1 และจัดเป็นกลุ่มย่อยๆทำกิจกรรมกับเพื่อนๆ ซึ่งเป็นค่ายที่จัดขึ้นเพื่อต้อนรับน้องๆเฟรชชี่ที่เพิ่งสอบติดและกำลังจะเข้ามาเป็นนิสิตปี 1 ของคณะโดยเฉพาะ",
      "duration": "4 วัน 3 คืน (ค้างคืนหรือไม่ค้างก็ได้)",
      "roles": "ปี 1 เป็นผู้เข้าร่วม ผู้จัดหลักๆเป็นรุ่นพี่ปี 2",
      "tips": "แนะนำให้ลองนอนค้างคืนดู จะได้รู้จักเพื่อนๆมากขึ้น ส่วนใหญ่ก็จะเป็นเพื่อนที่จะเจอกันไปตลอดทั้งเทอม หรือจะนอนเป็นบางคืนก็ได้เลือกได้เองเลย ของก็เตรียมไปให้ดีและติดตามเพจ escchula เพื่อติดตามข่าวสาร"
    }
  },
  {
    "id": "chula_friend",
    "title": "รับเพื่อนก้าวใหม่",
    "dateShort": "ส.ค.",
    "compareDate": "2026-08-01",
    "imageUrl": "https://images.unsplash.com/photo-1526976663112-001524a6bc41?q=80&w=600&auto=format&fit=crop",
    "type": "activity",
    "shortDesc": "ค่ายพบปะเพื่อนๆที่อยู่ต่างคณะซึ่งจะแบ่งเป็นบ้านๆ แล้วทำกิจกรรมด้วยกับ",
    "details": {
      "info": "กิจกรรมต้อนรับเฟรชชี่ระดับมหาวิทยาลัยของจุฬาฯ เพื่อที่จะได้รู้จักเพื่อนๆต่างคณะ จัดโดยองค์การบริหารสโมสรนิสิตจุฬาฯ (อบจ.)",
      "duration": "2 วัน",
      "roles": "ปี 1 เป็นผู้เข้าร่วม ผู้จัดหลักๆเป็นรุ่นพี่ปี 2",
      "tips": "ถ้าอยากที่จะรู้จักเพื่อนต่างคณะเยอะๆ ก็ลองเข้ากิจกรรมนี้ไปเมคเฟรนดู กิจกรรมอาจจะน่าเบื่อไปนิด แต่ได้รู้จัดเพื่อนต่างคณะแน่นอน"
    }
  },
  {
    "id": "start",
    "title": "เปิดเทอม",
    "dateShort": "ส.ค.",
    "compareDate": "2026-08-04",
    "imageUrl": "https://images.unsplash.com/photo-1434030216411-0b793f4b4173?q=80&w=600&auto=format&fit=crop",
    "type": "event",
    "shortDesc": "เริ่มเรียนวันแรกในฐานะเด็กใหม่ของคณะ"
  },
  {
    "id": "getReadyFreshy",
    "title": "กิจกรรม Get Ready Freshy",
    "dateShort": "ส.ค.",
    "compareDate": "2026-08-05",
    "imageUrl": "https://images.unsplash.com/photo-1526676037777-05a232554f77?q=80&w=600&auto=format&fit=crop",
    "type": "activity",
    "shortDesc": "กิจกรรมบรรยายเกี่ยวกับการเรียนปี 1",
    "details": {
      "info": "กิจกรรมแนะนำวิชาเรียนให้กับปี 1 ว่าควรเรียนอย่างไรบ้าง เตรียมตัวสอบอย่างไร ควรระวังวิชาไหนบ้าง",
      "duration": "3 วัน (ช่วงเย็น)",
      "roles": "ปี 1 นั่งฟังรับคำแนะนำจากรุ่นพี่ปี 2"
    }
  },
  {
    "id": "freshyGame",
    "title": "CU Freshy Game",
    "dateShort": "ส.ค.",
    "compareDate": "2026-08-18",
    "imageUrl": "https://images.unsplash.com/photo-1526676037777-05a232554f77?q=80&w=600&auto=format&fit=crop",
    "type": "activity",
    "shortDesc": "ประเพณีการแข่งขันกีฬาระหว่างคณะที่จัดขึ้นเพื่อต้อนรับน้องใหม่",
    "details": {
      "info": "กิจกรรมการแข่งขันกีฬาของปี 1 ระหว่างคณะภายในมหาวิทยาลัย หากอยากสมัครให้ติดตามเพจ อบจ. จุฬา",
      "duration": "5 วัน (ตามตารางการแข่งขัน)",
      "roles": "ลงแข่งเป็นตัวแทนคณะหรือเชียร์เพื่อนที่ลงแข่ง"
    }
  },
  {
    "id": "firstCoke",
    "title": "First Coke",
    "dateShort": "ส.ค.",
    "compareDate": "2026-08-23",
    "imageUrl": "https://images.unsplash.com/photo-1526676037777-05a232554f77?q=80&w=600&auto=format&fit=crop",
    "type": "activity",
    "shortDesc": "กิจกรรมดื่มของเหลวครั้งแรก",
    "details": {
      "info": "กิจกรรมที่รุ่นพี่พาน้องปี 1 ไปดื่มของเหลวเป็นครั้งแรก",
      "duration": "1 คืน",
      "roles": "ปี 1 ดื่ม ปี 2 จับยัด"
    }
  },
  {
    "id": "samarnmitr",
    "title": "งานสมานมิตร",
    "dateShort": "ส.ค.",
    "compareDate": "2026-08-25",
    "imageUrl": "https://images.unsplash.com/photo-1526676037777-05a232554f77?q=80&w=600&auto=format&fit=crop",
    "type": "activity",
    "shortDesc": "กลับบ้านครั้งแรกในฐานะศิษย์เก่า",
    "details": {
      "info": "ทุกคนอาาจะคิดถึงบ้านกัน ก็จะได้กลับกันเวลานี้แหละ อย่าลืมใส่เสื้อ Intania xxx ไปละ",
      "duration": "1 วัน",
      "roles": "ศิษย์เก่า"
    }
  },
  {
    "id": "midterm-1",
    "title": "สอบกลางภาคเทอม 1",
    "dateShort": "ต.ค.",
    "compareDate": "2026-12-15",
    "imageUrl": "https://images.unsplash.com/photo-1606326608606-aa0b62935f2b?q=80&w=600&auto=format&fit=crop",
    "type": "exam",
    "shortDesc": "สอบกลางภาคครั้งแรก",
    "details": {
      "info": "สอบเนื้อหาครึ่งแรก ประเดิมความรู้ที่เรียนมา",
      "tips": "ไปดูในแทปคำแนะนำได้เลย"
    }
  },
  {
    "id": "firstDrink",
    "title": "First Drink",
    "dateShort": "ต.ค.",
    "compareDate": "2026-10-22",
    "imageUrl": "https://images.unsplash.com/photo-1541339907198-e08756dedf3f?q=80&w=600&auto=format&fit=crop",
    "type": "activity",
    "shortDesc": "งานดื่มเครื่องดื่มที่แรงขึ้น",
    "details": {
      "info": "งานดื่มแอลกอฮอลครั้งแรกกับคณะ ซึ่งเละแน่นอน",
      "duration": "1 คืน",
      "roles": "ปี 1 ดื่ม ปี 2 จับยัด",
      "tips": "กินยาแก้แฮงค์ไปด้วยเพราะกินกันสุดแน่นอน พยายามดูแลตัวเองกันด้วยละ หรือถ้าไม่ก็หาคนพากลับให้ได้ก็พอ"
    }
  },
  {
    "id": "musicFest",
    "title": "Intania Music Fest",
    "dateShort": "พ.ย.",
    "compareDate": "2026-11-04",
    "imageUrl": "https://images.unsplash.com/photo-1541339907198-e08756dedf3f?q=80&w=600&auto=format&fit=crop",
    "type": "activity",
    "shortDesc": "งานเทศการดนตรีแห่ง Intania",
    "details": {
      "info": "งานดนตรีประจำปีของคณะวิศวกรรมศาสตร์ สามารถมากินข้าวฟรีได้",
      "duration": "1 วัน ช่วงเย็น",
      "roles": "นิสิตทุกคณะสามารถมาแจมกับกิจกรรมเทศกาลนี้ได้",
      "tips": "ใครชอบดนตรีก็มาฟังกันได้ แต่บอกเลยต่อแถวกินอาหารนานมาก เพราะมันฟรี"
    }
  },
  {
    "id": "jaturamitr",
    "title": "จตุรมิตรสามัคคี (ถ้ามี)",
    "dateShort": "พ.ย.",
    "compareDate": "2026-11-15",
    "imageUrl": "https://images.unsplash.com/photo-1541339907198-e08756dedf3f?q=80&w=600&auto=format&fit=crop",
    "type": "activity",
    "shortDesc": "งานฟุตบอลประเพณีสี่โรงเรียนชายล้วน",
    "details": {
      "info": "งานนี้ 2 ปีมีครั้ง แต่ถ้าปีนั้นๆมีก็จะอยู่ประมาณก่อนสอบ Final เพราะฉะนั้นก็เตรียมตัวกันดีๆ",
      "duration": "4 วัน ใน 1 สัปดาห์",
      "roles": "ศิษย์เก่า",
      "tips": "เข้าเดือนก่อนสัปดาห์นึงจะได้ไปเชียร์บอลกันได้อย่างมันส์"
    }
  },
  {
    "id": "final-1",
    "title": "สอบปลายภาค เทอม 2",
    "dateShort": "พ.ย.",
    "compareDate": "2026-11-24",
    "imageUrl": "https://images.unsplash.com/photo-1513258496099-48168024aec0?q=80&w=600&auto=format&fit=crop",
    "type": "exam",
    "shortDesc": "สอบปลายภาคเทอม 1",
    "details": {
      "info": "การสอบปลายภาคของเทอม 1 ซึ่งชี้ชะตาเกรดที่จะออกของเทอม 1",
      "tips": "อ่านในคำแนะนำรายวิชาได้เลย"
    }
  },
  {
    "id": "end",
    "title": "ปิดเทอม",
    "dateShort": "ธ.ค.",
    "compareDate": "2026-12-01",
    "imageUrl": "https://images.unsplash.com/photo-1434030216411-0b793f4b4173?q=80&w=600&auto=format&fit=crop",
    "type": "event",
    "shortDesc": "ปิดเทอมพักผ่อน หากิจกรรมทำ"
  },
  {
    "id": "funfeung-camp",
    "title": "ค่ายฟันเฟือง ฤดูหนาว",
    "dateShort": "ธ.ค.",
    "compareDate": "2026-12-14",
    "imageUrl": "https://images.unsplash.com/photo-1582213782179-e0d53f98f2ca?q=80&w=600&auto=format&fit=crop",
    "type": "activity",
    "shortDesc": "ค่ายสอนหนังสือ สร้างความรู้ความเข้าใจ แนะแนวทางในการศึกษาต่อในคณะวิศวกรรมศาสตร์",
    "details": {
      "info": "ค่ายสอนหนังสือที่ไปต่างจังหวัดเพื่อแนะแนวน้องๆเพื่อเข้าคณะวิศวกรรมศาสตร์",
      "duration": "2 สัปดาห์",
      "roles": "เป็นคนแนะแนวน้อง และมีส่วนการทำงานอื่นๆด้วย",
      "tips": "ทำกิจกรรมนี้เถอะ สนุกดี ได้นอนค้างคืนกับน้องด้วย"
    }
  },
  {
    "id": "larngear-camp",
    "title": "ค่ายลานเกียร์",
    "dateShort": "ธ.ค.",
    "compareDate": "2026-12-23",
    "imageUrl": "https://images.unsplash.com/photo-1582213782179-e0d53f98f2ca?q=80&w=600&auto=format&fit=crop",
    "type": "activity",
    "shortDesc": "กิจกรรมให้น้องมัธยมได้เรียนรู้เกี่ยวกับคณะวิศวกรรมศาสตร์",
    "details": {
      "info": "ค่ายนอนค้างคืนที่ให้น้องมีเรียนรู้เกี่ยวกับคณะวิศวกรรมศาสตร์ และทำกิจกรรมร่วมกับพี่ๆปี 1 อย่างเรา",
      "duration": "4 วัน 3 คืน",
      "roles": "ขอแค่ฝ่ายหลักๆนะ\n- ฝ่ายประสาน: ฝ่ายที่เป็นเฮดของทุกอย่าง ทำงานประสานด้วยและเป็นเฮดบ้านด้วย\n- ฝ่ายแผน: จัดการแผนการของค่าย ตารางเวลา การเดิน การไลน์แถว การขอสถานที่\n- ฝ่ายกิจกรรม: ฝ่ายที่คิดกิจกรรมหลักๆของค่ายให้มาทำกิจกรรมร่วมกัน\n- ฝ่ายวิชาการ: ฝ่ายที่ให้ความรู้กับน้องที่เข้าร่วมกิจกรรม\n- ฝ่ายทะเบียน: ฝ่ายที่จัดการคนรวมทั้งพี่และน้องว่ามีใครไปมาอย่างไรบ้าง\n- ฝ่ายพยาบาล: ฝ่ายที่ดูและเรื่องสุขภาพของน้องที่เข้าค่าย\n- ฝ่าย Security: ฝ่ายที่ดูแลความปลอดภันของทั้งค่าย",
      "tips": "ทำกิจกรรมนี้เถอะ สนุกดี ได้นอนค้างคืนกับน้องด้วย"
    }
  },
  {
    "id": "result",
    "title": "เกรดออก",
    "dateShort": "ธ.ค.",
    "compareDate": "2026-12-25",
    "imageUrl": "https://images.unsplash.com/photo-1434030216411-0b793f4b4173?q=80&w=600&auto=format&fit=crop",
    "type": "event",
    "shortDesc": "คริสต์มาสแดงเดือด เกรดเทอม 1 ออก"
  },
  {
    "id": "start",
    "title": "เปิดเทอม",
    "dateShort": "ม.ค.",
    "compareDate": "2027-01-04",
    "imageUrl": "https://images.unsplash.com/photo-1434030216411-0b793f4b4173?q=80&w=600&auto=format&fit=crop",
    "type": "event",
    "shortDesc": "เริ่มเรียนวันแรก เทอม 2"
  },
  {
    "id": "trip",
    "title": "เริ่มมีทริปกรุ๊ป",
    "dateShort": "ม.ค.",
    "compareDate": "2027-01-23",
    "imageUrl": "https://images.unsplash.com/photo-1582213782179-e0d53f98f2ca?q=80&w=600&auto=format&fit=crop",
    "type": "activity",
    "shortDesc": "ไปเที่ยวกับเพื่อนๆค้างคืนที่ต่างจังหวัด ชิวๆ",
    "details": {
      "info": "กิจกรรมที่ไปดื่มไปร่วมสนุกกับกรุ๊ปของตัวเอง",
      "duration": "3 วัน 2 คืน",
      "roles": "ปี 1 ผู้ร่วมกิจกรรม ปีโต ผู้จัดกิจกรรม",
      "tips": "ไปเถอะสนุกดี ได้สานสัมพันธ์ด้วย แล้วใครอยากเป็นเฮดกรุ๊ปก็มีเลือกกันงานนี้แหละ"
    }
  },
  {
    "id": "vidLoveVidU",
    "title": "Vid Love Vid U",
    "dateShort": "ก.พ.",
    "compareDate": "2027-02-13",
    "imageUrl": "https://images.unsplash.com/photo-1582213782179-e0d53f98f2ca?q=80&w=600&auto=format&fit=crop",
    "type": "activity",
    "shortDesc": "กิจกรรมวันวาเลนไทน์ของคณะวิศวกรรมศาสตร์และคณะวิทยาศาสตร์",
    "details": {
      "info": "กิจกรรมงานวันวาเลนไทน์ บรรยากาศดี ๆ ดนตรีเพราะ ๆ พร้อมทั้งบูธอาหารและบูธกิจกรรมมากมายให้ได้ร่วมสนุกกัน",
      "duration": "1 วัน (ช่วงเย็น)",
      "roles": "เข้าร่วมได้ทุกคนเลย",
      "tips": "ไปเถอะสนุกดี อาจจะได้แฟนก็ได้นะ แต่ส่วนใหญ่เป็นปีโตที่มากัน"
    }
  },
  {
    "id": "midterm-2",
    "title": "สอบกลางภาคเทอม 2",
    "dateShort": "ก.พ.",
    "compareDate": "2027-02-23",
    "imageUrl": "https://images.unsplash.com/photo-1606326608606-aa0b62935f2b?q=80&w=600&auto=format&fit=crop",
    "type": "exam",
    "shortDesc": "สอบกลางภาค",
    "details": {
      "info": "สอบเนื้อหาครึ่งแรก ประเดิมความรู้ที่เรียนมา",
      "tips": "ไปดูในแทปคำแนะนำได้เลย"
    }
  },
  {
    "id": "final-2",
    "title": "สอบปลายภาค เทอม 2",
    "dateShort": "เม.ย.",
    "compareDate": "2027-04-27",
    "imageUrl": "https://images.unsplash.com/photo-1513258496099-48168024aec0?q=80&w=600&auto=format&fit=crop",
    "type": "exam",
    "shortDesc": "สอบปลายภาคเทอม 2 เตรียมพร้อมจบปี 1",
    "details": {
      "info": "การสอบปลายภาคของเทอม 2 ซึ่งชี้ชะตาการเลือกภาคของเด็กภาครวมต่อไป",
      "tips": "อ่านในคำแนะนำรายวิชาได้เลย"
    }
  },
  {
    "id": "end",
    "title": "ปิดเทอม",
    "dateShort": "พ.ค.",
    "compareDate": "2027-05-13",
    "imageUrl": "https://images.unsplash.com/photo-1434030216411-0b793f4b4173?q=80&w=600&auto=format&fit=crop",
    "type": "event",
    "shortDesc": "ปิดเทอมพักผ่อน หากิจกรรมทำ"
  },
  {
    "id": "funfeung-camp",
    "title": "ค่ายฟันเฟือง ฤดูร้อน",
    "dateShort": "พ.ค.",
    "compareDate": "2027-05-16",
    "imageUrl": "https://images.unsplash.com/photo-1582213782179-e0d53f98f2ca?q=80&w=600&auto=format&fit=crop",
    "type": "activity",
    "shortDesc": "ค่ายสอนหนังสือ สร้างความรู้ความเข้าใจ แนะแนวทางในการศึกษาต่อในคณะวิศวกรรมศาสตร์",
    "details": {
      "info": "ค่ายสอนหนังสือที่ไปต่างจังหวัดเพื่อแนะแนวน้องๆเพื่อเข้าคณะวิศวกรรมศาสตร์",
      "duration": "2 สัปดาห์",
      "roles": "เป็นคนแนะแนวน้อง และมีส่วนการทำงานอื่นๆด้วย",
      "tips": "ทำกิจกรรมนี้เถอะ สนุกดี ได้นอนค้างคืนกับน้องด้วย"
    }
  },
  {
    "id": "fe-camp",
    "title": "ค่าย FE Camp",
    "dateShort": "พ.ค.",
    "compareDate": "2027-05-18",
    "imageUrl": "https://images.unsplash.com/photo-1582213782179-e0d53f98f2ca?q=80&w=600&auto=format&fit=crop",
    "type": "activity",
    "shortDesc": "กิจกรรมค่ายให้น้องมัธยมเตรียมพร้อมสำหรับการสอบ A-level ในปีถัดไป",
    "details": {
      "info": "ค่ายวิชาการที่สอน A-level ทุกวิชาที่ใช้เข้าคณะวิศวกรรมศาสตร์ ให้กับน้องๆมัธยม",
      "duration": "7 วัน",
      "roles": "ขอแค่ฝ่ายหลักๆนะ\n- ฝ่ายประสาน: ฝ่ายที่เป็นเฮดของทุกอย่าง ทำงานประสานด้วยและเป็นเฮดบ้านด้วย\n- ฝ่ายแผน: จัดการแผนการของค่าย ตารางเวลา การเดิน การไลน์แถว การขอสถานที่\n- ฝ่ายกิจกรรม: ฝ่ายที่คิดกิจกรรมหลักๆของค่ายให้มาทำกิจกรรมร่วมกัน\n- ฝ่ายวิชาการ: ฝ่ายที่สอน A-level ให้กับน้องๆ\n- ฝ่ายทะเบียน: ฝ่ายที่จัดการคนรวมทั้งพี่และน้องว่ามีใครไปมาอย่างไรบ้าง\n- ฝ่ายพยาบาล: ฝ่ายที่ดูและเรื่องสุขภาพของน้องที่เข้าค่าย",
      "tips": "ทำกิจกรรมนี้เถอะ สนุกดี ได้นอนค้างคืนกับน้องด้วย"
    }
  }
]